CPU/Part 01/alu.v
// Stimulus block
module testbench;

    // Declaring the connection variables 
    reg [7:0] data1, data2;
    wire [7:0] r;
    reg [2:0] sel;

    //Created an instance from the alu module
    alu alu1(data1,data2,r,sel);

    initial
    begin

        // Printing the result whenever we change the input
        $monitor("data1 = %b, data2 = %b     result=%b",data1,data2,r);
        $dumpfile("wavedata_grp18_aluOutput.vcd");
        $dumpvars(0,testbench);

        $display("Forward Operation : ");
        data1 = 8'b00_000_001;
        data2 = 8'b00_001_011;
        sel = 3'b000;
        
        #5;
        $display("ADD Operation : ");
        data1 = 8'b00_000_001;
        data2 = 8'b00_001_110;
        sel = 3'b001;

        #5;
        $display("Bitwise AND Operation : ");
        data1 = 8'b00_000_001;
        data2 = 8'b00_000_010;
        sel = 3'b010;

        #5;
        $display("Bitwise OR Operation : ");
        data1 = 8'b00_001_001;
        data2 = 8'b00_001_111;
        sel = 3'b011;
       
        
    end
endmodule

//*********************************************************** 8-bit ALU *****************************************************************//
// 8-bit ALU module
module alu (DATA1, DATA2, RESULT, SELECT);

    // Port Declaration
    input [7:0] DATA1, DATA2;
    input [2:0] SELECT;
    output reg [7:0] RESULT;
    wire [7:0] fwdResult, addResult, andResult, orResult;

    // Instantiating the modules
    FWD fwd1(DATA2, fwdResult);                          // Forward Function
    ADD add1(DATA1, DATA2, addResult);                   // ADD function
    AND and1(DATA1, DATA2, andResult);                   // Bitwise AND function
    OR or1(DATA1, DATA2, orResult);                      // Bitwise OR function

    // This always block will execute whenever we change the DATA1, DATA2 & SELECT inputs
    always @(fwdResult, addResult, andResult, orResult) begin
    // Case structure to simulate the mux's operations
    case (SELECT)
        3'b000 :  RESULT = fwdResult;
        3'b001 :  RESULT = addResult;
        3'b010 :  RESULT = andResult;
        3'b011 :  RESULT = orResult;
        default:  RESULT = 8'b00000000;
    endcase
    end 

endmodule

// module to perform forward instruction 
module FWD(DATA2, RESULT);

    // Port Declaration
    input [7:0] DATA2;
    output [7:0] RESULT;

        // Updating the result after #1 unit time delay
        assign #1 RESULT = DATA2;

endmodule

// module to perform add instruction 
module ADD(DATA1, DATA2, RESULT);

    // Port Declaration
    input [7:0] DATA1, DATA2;
    output [7:0] RESULT;

        // Updating the result after #2 unit time delay
        assign #2 RESULT = DATA1 + DATA2;

endmodule

// module to perform and instruction 
module AND(DATA1, DATA2, RESULT);

    // Port Declaration
    input [7:0] DATA1, DATA2;
    output [7:0] RESULT;

        // Updating the result after #1 unit time delay
        assign #1 RESULT = DATA1 & DATA2;

endmodule

// module to perform or instruction 
module OR(DATA1, DATA2, RESULT);

    // Port Declaration
    input [7:0] DATA1, DATA2;
    output [7:0] RESULT;

        // Updating the result after #1 unit time delay
        assign #1 RESULT = DATA1 | DATA2;

endmodule

CPU/Part 01/wavedata_grp18_aluOutput.vcd
$date
	Wed Jan 12 11:21:40 2022
$end
$version
	Icarus Verilog
$end
$timescale
	1s
$end
$scope module testbench $end
$var wire 8 ! r [7:0] $end
$var reg 8 " data1 [7:0] $end
$var reg 8 # data2 [7:0] $end
$var reg 3 $ sel [2:0] $end
$scope module alu1 $end
$var wire 8 % DATA1 [7:0] $end
$var wire 8 & DATA2 [7:0] $end
$var wire 3 ' SELECT [2:0] $end
$var wire 8 ( orResult [7:0] $end
$var wire 8 ) fwdResult [7:0] $end
$var wire 8 * andResult [7:0] $end
$var wire 8 + addResult [7:0] $end
$var reg 8 , RESULT [7:0] $end
$scope module add1 $end
$var wire 8 - DATA1 [7:0] $end
$var wire 8 . DATA2 [7:0] $end
$var wire 8 / RESULT [7:0] $end
$upscope $end
$scope module and1 $end
$var wire 8 0 DATA1 [7:0] $end
$var wire 8 1 DATA2 [7:0] $end
$var wire 8 2 RESULT [7:0] $end
$upscope $end
$scope module fwd1 $end
$var wire 8 3 DATA2 [7:0] $end
$var wire 8 4 RESULT [7:0] $end
$upscope $end
$scope module or1 $end
$var wire 8 5 DATA1 [7:0] $end
$var wire 8 6 DATA2 [7:0] $end
$var wire 8 7 RESULT [7:0] $end
$upscope $end
$upscope $end
$upscope $end
$enddefinitions $end
#0
$dumpvars
bx 7
b1011 6
b1 5
bx 4
b1011 3
bx 2
b1011 1
b1 0
bx /
b1011 .
b1 -
bx ,
bx +
bx *
bx )
bx (
b0 '
b1011 &
b1 %
b0 $
b1011 #
b1 "
bx !
$end
#1
b1011 !
b1011 ,
b1011 (
b1011 7
b1 *
b1 2
b1011 )
b1011 4
#2
b1100 +
b1100 /
#5
b1 $
b1 '
b1110 #
b1110 &
b1110 .
b1110 1
b1110 3
b1110 6
#6
b1100 !
b1100 ,
b0 *
b0 2
b1111 (
b1111 7
b1110 )
b1110 4
#7
b1111 !
b1111 ,
b1111 +
b1111 /
#10
b10 $
b10 '
b10 #
b10 &
b10 .
b10 1
b10 3
b10 6
#11
b0 !
b0 ,
b11 (
b11 7
b10 )
b10 4
#12
b11 +
b11 /
#15
b11 $
b11 '
b1111 #
b1111 &
b1111 .
b1111 1
b1111 3
b1111 6
b1001 "
b1001 %
b1001 -
b1001 0
b1001 5
#16
b1111 !
b1111 ,
b1001 *
b1001 2
b1111 (
b1111 7
b1111 )
b1111 4
#17
b11000 +
b11000 /
